cobra/__init__.py
cobra/utils.py
cobra/version.py
cobra/evaluation/__init__.py
cobra/evaluation/evaluator.py
cobra/evaluation/pigs_tables.py
cobra/evaluation/plotting_utils.py
cobra/model_building/__init__.py
cobra/model_building/forward_selection.py
cobra/model_building/models.py
cobra/model_building/univariate_selection.py
cobra/preprocessing/__init__.py
cobra/preprocessing/categorical_data_processor.py
cobra/preprocessing/kbins_discretizer.py
cobra/preprocessing/preprocessor.py
cobra/preprocessing/target_encoder.py
pythonpredictions_cobra-1.1.1.dist-info/LICENSE
pythonpredictions_cobra-1.1.1.dist-info/METADATA
pythonpredictions_cobra-1.1.1.dist-info/WHEEL
pythonpredictions_cobra-1.1.1.dist-info/top_level.txt
pythonpredictions_cobra-1.1.1.dist-info/RECORD
