Metadata-Version: 2.1
Name: pythonpredictions-cobra
Version: 1.1.1
Summary: A Python package to build predictive linear and logistic regression models focused on performance and interpretation.
Home-page: https://github.com/PythonPredictions/cobra
Author: Python Predictions
Author-email: cobra@pythonpredictions.com
License: MIT
License-File: LICENSE
Requires-Dist: numpy (>=1.19.4)
Requires-Dist: pandas (<2.0,>=1.1.5)
Requires-Dist: scipy (>=1.5.4)
Requires-Dist: scikit-learn (>=0.24.1)
Requires-Dist: matplotlib (>=3.4.3)
Requires-Dist: seaborn (>=0.11.0)
Requires-Dist: tqdm (>=4.62.2)
